django_filer-3.4.3.dist-info/licenses/LICENSE
filer/__init__.py
filer/apps.py
filer/cache.py
filer/settings.py
filer/storage.py
filer/thumbnail_processors.py
filer/urls.py
filer/validation.py
filer/views.py
filer/admin/__init__.py
filer/admin/clipboardadmin.py
filer/admin/fileadmin.py
filer/admin/folderadmin.py
filer/admin/forms.py
filer/admin/imageadmin.py
filer/admin/permissionadmin.py
filer/admin/permissions.py
filer/admin/thumbnailoptionadmin.py
filer/admin/tools.py
filer/admin/views.py
filer/admin/patched/__init__.py
filer/admin/patched/admin_utils.py
filer/contrib/__init__.py
filer/contrib/clamav/__init__.py
filer/contrib/django_cms/__init__.py
filer/contrib/django_cms/cms_toolbars.py
filer/fields/__init__.py
filer/fields/file.py
filer/fields/folder.py
filer/fields/image.py
filer/fields/multistorage_file.py
filer/locale/README
filer/locale/ar/LC_MESSAGES/django.mo
filer/locale/ar/LC_MESSAGES/django.po
filer/locale/bg/LC_MESSAGES/django.mo
filer/locale/bg/LC_MESSAGES/django.po
filer/locale/ca/LC_MESSAGES/django.mo
filer/locale/ca/LC_MESSAGES/django.po
filer/locale/cs/LC_MESSAGES/django.mo
filer/locale/cs/LC_MESSAGES/django.po
filer/locale/de/LC_MESSAGES/django.mo
filer/locale/de/LC_MESSAGES/django.po
filer/locale/en/LC_MESSAGES/django.mo
filer/locale/en/LC_MESSAGES/django.po
filer/locale/es/LC_MESSAGES/django.mo
filer/locale/es/LC_MESSAGES/django.po
filer/locale/et/LC_MESSAGES/django.mo
filer/locale/et/LC_MESSAGES/django.po
filer/locale/eu/LC_MESSAGES/django.mo
filer/locale/eu/LC_MESSAGES/django.po
filer/locale/fa/LC_MESSAGES/django.mo
filer/locale/fa/LC_MESSAGES/django.po
filer/locale/fi/LC_MESSAGES/django.mo
filer/locale/fi/LC_MESSAGES/django.po
filer/locale/fr/LC_MESSAGES/django.mo
filer/locale/fr/LC_MESSAGES/django.po
filer/locale/gl/LC_MESSAGES/django.mo
filer/locale/gl/LC_MESSAGES/django.po
filer/locale/he/LC_MESSAGES/django.mo
filer/locale/he/LC_MESSAGES/django.po
filer/locale/hr/LC_MESSAGES/django.mo
filer/locale/hr/LC_MESSAGES/django.po
filer/locale/hu/LC_MESSAGES/django.mo
django_filer-3.4.3.dist-info/METADATA
django_filer-3.4.3.dist-info/WHEEL
django_filer-3.4.3.dist-info/top_level.txt
django_filer-3.4.3.dist-info/RECORD
