Metadata-Version: 2.4
Name: django-filer
Version: 3.4.3
Summary: A file management application for django that makes handling of files and images a breeze.
Author-email: Divio AG <info@divio.ch>
Maintainer-email: Django CMS Association and contributors <info@django-cms.org>
License: BSD-3-Clause
Project-URL: Homepage, https://github.com/django-cms/django-filer
Classifier: Development Status :: 5 - Production/Stable
Classifier: Environment :: Web Environment
Classifier: Intended Audience :: Developers
Classifier: License :: OSI Approved :: BSD License
Classifier: Operating System :: OS Independent
Classifier: Programming Language :: Python
Classifier: Programming Language :: Python :: 3
Classifier: Programming Language :: Python :: 3.10
Classifier: Programming Language :: Python :: 3.11
Classifier: Programming Language :: Python :: 3.12
Classifier: Programming Language :: Python :: 3.13
Classifier: Programming Language :: Python :: 3.14
Classifier: Framework :: Django
Classifier: Framework :: Django :: 3.2
Classifier: Framework :: Django :: 4.2
Classifier: Framework :: Django :: 5.0
Classifier: Framework :: Django :: 5.1
Classifier: Framework :: Django :: 5.2
Classifier: Framework :: Django :: 6.0
Classifier: Framework :: Django CMS
Classifier: Framework :: Django CMS :: 3.11
Classifier: Framework :: Django CMS :: 4.0
Classifier: Framework :: Django CMS :: 4.1
Classifier: Framework :: Django CMS :: 5.0
Classifier: Topic :: Internet :: WWW/HTTP
Classifier: Topic :: Internet :: WWW/HTTP :: Dynamic Content
Classifier: Topic :: Software Development
Classifier: Topic :: Software Development :: Libraries
Requires-Python: >=3.8
License-File: LICENSE
Requires-Dist: django>=3.2
Requires-Dist: django-polymorphic<5.0
Requires-Dist: easy-thumbnails[svg]
Requires-Dist: svglib~=1.5.1
Provides-Extra: heif
Requires-Dist: pillow-heif; extra == "heif"
Dynamic: license-file
